webtextcrawler/__init__.py
webtextcrawler/webtextcrawler.py
webtextcrawler/resources/language_mapping.pkl
webtextcrawler-1.0.2.dist-info/LICENSE
webtextcrawler-1.0.2.dist-info/METADATA
webtextcrawler-1.0.2.dist-info/WHEEL
webtextcrawler-1.0.2.dist-info/top_level.txt
webtextcrawler-1.0.2.dist-info/RECORD
