Metadata-Version: 2.1
Name: webtextcrawler
Version: 1.0.2
Summary: Python project for crawling the web and extracting text.
Author: Carlo Moro
Author-email: Carlo Moro <cnmoro@gmail.com>
Project-URL: Homepage, https://github.com/cnmoro
Project-URL: Bug Tracker, https://github.com/cnmoro
Classifier: Programming Language :: Python :: 3
Classifier: License :: OSI Approved :: MIT License
Classifier: Operating System :: OS Independent
Requires-Python: >=3.7
License-File: LICENSE
Requires-Dist: langdetect
Requires-Dist: beautifulsoup4
Requires-Dist: requests
Requires-Dist: jusText
